{
"skeleton": { "hash": "BeRkAWbsfZ0r4NQ5HON6dSMUwxY", "spine": "3.6.53", "width": 57.22, "height": 66.18, "images": "" },
"bones": [
	{ "name": "root", "x": -0.19, "y": 0.66 },
	{ "name": "Body", "parent": "root", "rotation": 88.27, "x": -0.32, "y": 28.53 },
	{ "name": "Hands", "parent": "Body", "rotation": -92.02, "x": 16.95, "y": -9.72 },
	{ "name": "Head", "parent": "Body", "length": 8.97, "rotation": 1.67, "x": 23.76, "y": -0.7 },
	{ "name": "Left Arm", "parent": "Hands", "rotation": 2.34, "x": -0.8, "y": -5.54, "color": "ff3f00ff" },
	{ "name": "Left Leg Container", "parent": "root", "length": 6.1, "rotation": -12.31, "x": -6.53, "y": 1.36 },
	{ "name": "Left Foot", "parent": "Left Leg Container", "rotation": 11.16, "x": 6.85, "y": 1.07, "color": "ff3f00ff" },
	{ "name": "Left Leg", "parent": "Left Leg Container", "rotation": 11.16, "x": 0.01, "y": 1.87, "color": "ff3f00ff" },
	{ "name": "Right Arm", "parent": "Hands", "rotation": 2.34, "x": 12.62, "y": 0.88, "color": "ff3f00ff" },
	{ "name": "Right Leg Container", "parent": "root", "length": 6.75, "rotation": -9.55, "x": 2.27, "y": 1.1 },
	{ "name": "Right Foot", "parent": "Right Leg Container", "rotation": 9.55, "x": 8.61, "y": 1.24, "color": "ff3f00ff" },
	{ "name": "Right Leg", "parent": "Right Leg Container", "rotation": 9.55, "x": 0.46, "y": 2.31, "color": "ff3f00ff" },
	{ "name": "bone2", "parent": "Body", "length": 12.65, "rotation": -174.85, "x": -0.3, "y": -5.21 },
	{ "name": "bone3", "parent": "bone2", "length": 12.71, "rotation": -3.96, "x": 13.91, "y": -0.11 },
	{ "name": "bone4", "parent": "bone3", "length": 6.03, "rotation": 78.72, "x": 13.48, "y": -0.01 },
	{ "name": "bone5", "parent": "Body", "length": 9, "rotation": -88.35, "x": 20.39, "y": -6.33 },
	{ "name": "bone6", "parent": "bone5", "length": 10.26, "x": 13.64, "y": 0.81 },
	{ "name": "bone7", "parent": "Body", "length": 12.56, "rotation": -174.3, "x": 0.22, "y": 2.11 },
	{ "name": "bone8", "parent": "bone7", "length": 14.28, "rotation": -3.97, "x": 13.49, "y": -0.21 },
	{ "name": "bone9", "parent": "bone8", "length": 4.84, "rotation": 75.9, "x": 14.88, "y": 0.22 },
	{ "name": "bone10", "parent": "Body", "length": 10.51, "rotation": 89.77, "x": 18.84, "y": 4.97 },
	{ "name": "bone11", "parent": "bone10", "length": 11.33, "rotation": -0.06, "x": 11.41, "y": -0.09 }
],
"slots": [
	{ "name": "Forearm", "bone": "root", "attachment": "Survivor Sheet" },
	{ "name": "Arm", "bone": "root", "attachment": "Survivor Sheet" },
	{ "name": "Calf", "bone": "root", "attachment": "Survivor Sheet" },
	{ "name": "Leg", "bone": "root", "attachment": "Survivor Sheet" },
	{ "name": "Foot", "bone": "root", "attachment": "Survivor Sheet" },
	{ "name": "Body", "bone": "root", "attachment": "Survivor Sheet" },
	{ "name": "Calf2", "bone": "root", "attachment": "Survivor Sheet" },
	{ "name": "Leg2", "bone": "root", "attachment": "Survivor Sheet" },
	{ "name": "Foot2", "bone": "root", "attachment": "Survivor Sheet2" },
	{ "name": "Head", "bone": "root", "attachment": "Survivor Sheet" },
	{ "name": "Gun", "bone": "Hands", "attachment": "sks" },
	{ "name": "Forearm2", "bone": "root", "attachment": "Survivor Sheet" },
	{ "name": "Arm2", "bone": "root", "attachment": "Survivor Sheet" }
],
"ik": [
	{
		"name": "Left Arm",
		"order": 1,
		"bones": [ "bone10", "bone11" ],
		"target": "Left Arm"
	},
	{
		"name": "Left Foot",
		"order": 5,
		"bones": [ "bone9" ],
		"target": "Left Foot"
	},
	{
		"name": "Left Leg",
		"order": 4,
		"bones": [ "bone7", "bone8" ],
		"target": "Left Leg",
		"bendPositive": false
	},
	{
		"name": "Right Arm",
		"order": 0,
		"bones": [ "bone5", "bone6" ],
		"target": "Right Arm"
	},
	{
		"name": "Right Foot",
		"order": 3,
		"bones": [ "bone4" ],
		"target": "Right Foot"
	},
	{
		"name": "Right Leg",
		"order": 2,
		"bones": [ "bone2", "bone3" ],
		"target": "Right Leg",
		"bendPositive": false
	}
],
"skins": {
	"default": {
		"Arm": {
			"Survivor Sheet": {
				"type": "mesh",
				"uvs": [ 0.7238, 0.08532, 0.69823, 0.15017, 0.69539, 0.30005, 0.7103, 0.32743, 0.73942, 0.32743, 0.75078, 0.30005, 0.75078, 0.0882 ],
				"triangles": [ 1, 0, 6, 5, 1, 6, 5, 2, 1, 3, 2, 5, 4, 3, 5 ],
				"vertices": [ 1, 15, -1.56, 0.25, 1, 1, 15, 2.77, 3.87, 1, 1, 15, 12.95, 4.5, 1, 1, 15, 14.86, 2.48, 1, 1, 15, 14.95, -1.54, 1, 1, 15, 13.13, -3.15, 1, 1, 15, -1.28, -3.47, 1 ],
				"hull": 7,
				"edges": [ 0, 2, 2, 4, 4, 6, 6, 8, 8, 10, 10, 12, 0, 12 ],
				"width": 276,
				"height": 136
			}
		},
		"Arm2": {
			"Survivor Sheet": {
				"type": "mesh",
				"uvs": [ 0.69559, 0.29625, 0.71029, 0.32359, 0.73907, 0.31986, 0.75009, 0.29128, 0.7507, 0.0937, 0.7207, 0.09494, 0.69804, 0.14465 ],
				"triangles": [ 4, 6, 5, 3, 6, 4, 3, 0, 6, 2, 0, 3, 1, 0, 2 ],
				"vertices": [ 1, 20, 10.75, -4.91, 1, 1, 20, 12.53, -2.82, 1, 1, 20, 12.12, 1.14, 1, 1, 20, 10.12, 2.59, 1, 1, 20, -3.31, 2.16, 1, 1, 20, -3.07, -1.98, 1, 1, 20, 0.43, -4.97, 1 ],
				"hull": 7,
				"edges": [ 0, 2, 2, 4, 4, 6, 6, 8, 8, 10, 10, 12, 0, 12 ],
				"width": 276,
				"height": 136
			}
		},
		"Body": {
			"Survivor Sheet": {
				"type": "mesh",
				"uvs": [ 0.75745, 0.42456, 0.79999, 0.48212, 0.82761, 0.48363, 0.86941, 0.38063, 0.87538, 0.20947, 0.88807, 0.15494, 0.88284, 0.07769, 0.84627, 0.0065, 0.78283, 0.0065, 0.75596, 0.05951, 0.74924, 0.08981, 0.74924, 0.22007, 0.75372, 0.25642 ],
				"triangles": [ 8, 6, 5, 6, 8, 7, 5, 11, 10, 5, 9, 8, 9, 5, 10, 4, 11, 5, 12, 11, 4, 3, 12, 4, 0, 12, 3, 2, 1, 0, 3, 2, 0 ],
				"vertices": [ 1, 1, -2.36, 6.6, 1, 1, 1, -5.37, 0.33, 1, 1, 1, -5.36, -3.49, 1, 1, 1, 1.82, -9.04, 1, 1, 1, 13.48, -9.51, 1, 1, 1, 17.24, -11.15, 1, 1, 1, 22.47, -10.27, 1, 1, 1, 27.15, -5.08, 1, 1, 1, 26.89, 3.67, 1, 1, 1, 23.17, 7.27, 1, 1, 1, 21.09, 8.13, 1, 1, 1, 12.23, 7.87, 1, 1, 1, 9.78, 7.17, 1 ],
				"hull": 13,
				"edges": [ 0, 2, 2, 4, 4, 6, 6, 8, 8, 10, 10, 12, 12, 14, 14, 16, 16, 18, 18, 20, 20, 22, 22, 24, 0, 24 ],
				"width": 276,
				"height": 136
			}
		},
		"Calf": {
			"Survivor Sheet": {
				"type": "mesh",
				"uvs": [ 0.81501, 0.74864, 0.83343, 0.71488, 0.86017, 0.71247, 0.86849, 0.739, 0.87384, 0.91747, 0.85364, 0.95244, 0.82393, 0.95364, 0.81323, 0.92229 ],
				"triangles": [ 1, 2, 3, 0, 1, 3, 0, 3, 4, 7, 0, 4, 5, 7, 4, 6, 7, 5 ],
				"vertices": [ 1, 13, -0.54, -4.12, 1, 1, 13, -2.24, -2.16, 1, 1, 13, -2.8, 1.49, 1, 1, 13, -1.13, 2.83, 1, 1, 13, 10.86, 4.87, 1, 1, 13, 13.52, 2.35, 1, 1, 13, 14.04, -1.71, 1, 1, 13, 12.08, -3.41, 1 ],
				"hull": 8,
				"edges": [ 0, 2, 2, 4, 4, 6, 6, 8, 8, 10, 10, 12, 12, 14, 0, 14 ],
				"width": 276,
				"height": 136
			}
		},
		"Calf2": {
			"Survivor Sheet": {
				"type": "mesh",
				"uvs": [ 0.81231, 0.77563, 0.82774, 0.71455, 0.86324, 0.71455, 0.87559, 0.90719, 0.85552, 0.95574, 0.81539, 0.95104 ],
				"triangles": [ 3, 5, 0, 0, 1, 2, 2, 3, 0, 4, 5, 3 ],
				"vertices": [ 1, 18, 3.32, -4.04, 1, 1, 18, -0.99, -2.26, 1, 1, 18, -1.39, 2.62, 1, 1, 18, 11.52, 5.39, 1, 1, 18, 15.04, 2.9, 1, 1, 18, 15.18, -2.64, 1 ],
				"hull": 6,
				"edges": [ 0, 2, 2, 4, 4, 6, 6, 8, 8, 10, 0, 10 ],
				"width": 276,
				"height": 136
			}
		},
		"Foot": {
			"Survivor Sheet": {
				"type": "mesh",
				"uvs": [ 0.73461, 0.99487, 0.8146, 0.9939, 0.8146, 0.95185, 0.79244, 0.91957, 0.73654, 0.92153 ],
				"triangles": [ 0, 3, 2, 0, 4, 3, 1, 0, 2 ],
				"vertices": [ 1, 14, -1.11, -3.35, 1, 1, 14, 9.7, -1.13, 1, 1, 14, 9.14, 1.68, 1, 1, 14, 5.71, 3.23, 1, 1, 14, -1.83, 1.59, 1 ],
				"hull": 5,
				"edges": [ 0, 2, 2, 4, 4, 6, 6, 8, 0, 8 ],
				"width": 276,
				"height": 136
			}
		},
		"Foot2": {
			"Survivor Sheet": {
				"type": "mesh",
				"uvs": [ 0.73519, 0.99153, 0.814, 0.98706, 0.81589, 0.94995, 0.79382, 0.91925, 0.73614, 0.92245 ],
				"triangles": [ 2, 0, 3, 0, 4, 3, 1, 0, 2 ],
				"vertices": [ 1, 19, -1.58, -3.04, 1, 1, 19, 8.95, -0.32, 1, 1, 19, 8.65, 2.19, 1, 1, 19, 5.21, 3.55, 1, 1, 19, -2.5, 1.57, 1 ],
				"hull": 5,
				"edges": [ 0, 2, 2, 4, 4, 6, 6, 8, 0, 8 ],
				"width": 276,
				"height": 136
			},
			"Survivor Sheet2": {
				"type": "mesh",
				"path": "Survivor Sheet",
				"uvs": [ 0.73519, 0.91989, 0.79288, 0.91733, 0.79446, 0.86359, 0.78468, 0.84696, 0.7519, 0.84632, 0.73456, 0.87767 ],
				"triangles": [ 4, 3, 2, 5, 2, 0, 4, 2, 5, 1, 0, 2 ],
				"vertices": [ 1, 19, -1.52, -3.29, 1, 1, 19, 6.2, -1.35, 1, 1, 19, 5.6, 2.26, 1, 1, 19, 4.03, 3.06, 1, 1, 19, -0.39, 2.1, 1, 1, 19, -2.25, -0.51, 1 ],
				"hull": 6,
				"edges": [ 0, 2, 2, 4, 4, 6, 6, 8, 8, 10, 0, 10 ],
				"width": 276,
				"height": 136
			}
		},
		"Forearm": {
			"Survivor Sheet": {
				"type": "mesh",
				"uvs": [ 0.8746, 0.58436, 0.96607, 0.56616, 0.99895, 0.59042, 0.99895, 0.64623, 0.96427, 0.66564, 0.8734, 0.65836 ],
				"triangles": [ 4, 1, 2, 4, 0, 1, 3, 4, 2, 5, 0, 4 ],
				"vertices": [ 1, 16, -2.43, 2.97, 1, 1, 16, 10.23, 3.7, 1, 1, 16, 14.7, 1.87, 1, 1, 16, 14.55, -1.92, 1, 1, 16, 9.72, -3.05, 1, 1, 16, -2.79, -2.05, 1 ],
				"hull": 6,
				"edges": [ 0, 2, 2, 4, 4, 6, 6, 8, 8, 10, 0, 10 ],
				"width": 276,
				"height": 136
			}
		},
		"Forearm2": {
			"Survivor Sheet": {
				"type": "mesh",
				"uvs": [ 0.87159, 0.49837, 0.8839, 0.47925, 0.9955, 0.47484, 0.99622, 0.5219, 0.98101, 0.57043, 0.88535, 0.56895, 0.87231, 0.55425 ],
				"triangles": [ 1, 2, 3, 0, 5, 6, 1, 5, 0, 1, 3, 5, 4, 5, 3 ],
				"vertices": [ 1, 21, -2.44, 1.8, 1, 1, 21, -0.75, 3.1, 1, 1, 21, 14.65, 3.45, 1, 1, 21, 14.76, 0.25, 1, 1, 21, 12.67, -3.06, 1, 1, 21, -0.53, -3, 1, 1, 21, -2.33, -2, 1 ],
				"hull": 7,
				"edges": [ 0, 2, 2, 4, 4, 6, 6, 8, 8, 10, 10, 12, 0, 12 ],
				"width": 276,
				"height": 136
			}
		},
		"Gun": {
			"m4a1": {
				"type": "mesh",
				"uvs": [ 1, 1, 0, 1, 0, 0, 1, 0 ],
				"triangles": [ 1, 2, 3, 1, 3, 0 ],
				"vertices": [ 1, 2, 29.46, -9.87, 1, 1, 2, -12.42, -11.58, 1, 1, 2, -13.09, 4.89, 1, 1, 2, 28.79, 6.6, 1 ],
				"hull": 4,
				"edges": [ 0, 2, 2, 4, 4, 6, 0, 6 ],
				"width": 178,
				"height": 70
			},
			"mp5": {
				"type": "mesh",
				"uvs": [ 1, 1, 0, 1, 0, 0, 1, 0 ],
				"triangles": [ 1, 2, 3, 1, 3, 0 ],
				"vertices": [ 17.13, -9.24, -12.55, -10.29, -13.05, 3.91, 16.63, 4.96 ],
				"hull": 4,
				"edges": [ 0, 2, 2, 4, 4, 6, 0, 6 ],
				"width": 140,
				"height": 67
			},
			"sks": {
				"type": "mesh",
				"uvs": [ 1, 1, 0, 1, 0, 0, 1, 0 ],
				"triangles": [ 1, 2, 3, 1, 3, 0 ],
				"vertices": [ 37.92, -3.13, -13.02, -5.27, -13.44, 4.74, 37.5, 6.87 ],
				"hull": 4,
				"edges": [ 0, 2, 2, 4, 4, 6, 0, 6 ],
				"width": 275,
				"height": 54
			}
		},
		"Head": {
			"Survivor Sheet": {
				"type": "mesh",
				"uvs": [ 0.92819, 0.23336, 0.97498, 0.23568, 1, 0.16542, 0.99895, 0.03803, 0.97803, 0.00638, 0.91716, 0.00329, 0.89547, 0.03494, 0.89928, 0.17314 ],
				"triangles": [ 7, 6, 2, 4, 6, 5, 3, 6, 4, 2, 6, 3, 0, 7, 2, 1, 0, 2 ],
				"vertices": [ 1, 3, -2.2, 2.26, 1, 1, 3, -2.35, -4.2, 1, 1, 3, 2.42, -7.65, 1, 1, 3, 11.09, -7.51, 1, 1, 3, 13.24, -4.62, 1, 1, 3, 13.45, 3.78, 1, 1, 3, 11.3, 6.77, 1, 1, 3, 1.9, 6.25, 1 ],
				"hull": 8,
				"edges": [ 0, 2, 2, 4, 4, 6, 6, 8, 8, 10, 10, 12, 12, 14, 0, 14 ],
				"width": 276,
				"height": 136
			}
		},
		"Leg": {
			"Survivor Sheet": {
				"type": "mesh",
				"uvs": [ 0.81618, 0.50818, 0.83213, 0.47199, 0.86594, 0.4704, 0.87485, 0.52722, 0.87347, 0.66387, 0.85747, 0.71385, 0.82368, 0.71195, 0.81328, 0.67001 ],
				"triangles": [ 2, 0, 1, 2, 3, 0, 3, 7, 0, 3, 4, 7, 5, 6, 7, 4, 5, 7 ],
				"vertices": [ 1, 12, -0.13, -3.29, 1, 1, 12, -2.24, -0.39, 1, 1, 12, -1.97, 4.26, 1, 1, 12, 1.96, 5.12, 1, 1, 12, 11.22, 4.25, 1, 1, 12, 14.44, 1.78, 1, 1, 12, 13.94, -2.86, 1, 1, 12, 10.98, -4.05, 1 ],
				"hull": 8,
				"edges": [ 0, 2, 2, 4, 4, 6, 6, 8, 8, 10, 10, 12, 12, 14, 0, 14 ],
				"width": 276,
				"height": 136
			}
		},
		"Leg2": {
			"Survivor Sheet": {
				"type": "mesh",
				"uvs": [ 0.7469, 0.52475, 0.77021, 0.47457, 0.79565, 0.476, 0.81614, 0.54052, 0.81048, 0.6839, 0.78717, 0.72692, 0.76103, 0.71402, 0.74407, 0.66527 ],
				"triangles": [ 2, 3, 0, 7, 0, 3, 2, 0, 1, 4, 6, 3, 6, 7, 3, 5, 6, 4 ],
				"vertices": [ 1, 17, 1.99, -4.2, 1, 1, 17, -1.4, -0.96, 1, 1, 17, -1.28, 2.55, 1, 1, 17, 3.13, 5.35, 1, 1, 17, 12.88, 4.5, 1, 1, 17, 15.78, 1.26, 1, 1, 17, 14.87, -2.34, 1, 1, 17, 11.54, -4.66, 1 ],
				"hull": 8,
				"edges": [ 0, 2, 2, 4, 4, 6, 6, 8, 8, 10, 10, 12, 12, 14, 0, 14 ],
				"width": 276,
				"height": 136
			}
		}
	}
},
"animations": {
	"Crouch": {
		"slots": {
			"Foot2": {
				"attachment": [
					{ "time": 0, "name": "Survivor Sheet" }
				]
			}
		},
		"bones": {
			"Body": {
				"rotate": [
					{ "time": 0, "angle": 0 }
				],
				"translate": [
					{ "time": 0, "x": -1.09, "y": -11.11 },
					{ "time": 0.4333, "x": -2.27, "y": -9.32 },
					{ "time": 0.9667, "x": -0.65, "y": -10.13 },
					{ "time": 1.3333, "x": -1.09, "y": -11.11 }
				]
			},
			"Right Leg Container": {
				"translate": [
					{ "time": 0, "x": 1.98, "y": 0 }
				]
			},
			"Left Leg Container": {
				"rotate": [
					{ "time": 1.3333, "angle": 0 }
				],
				"translate": [
					{ "time": 0, "x": -5.19, "y": 0, "curve": "stepped" },
					{ "time": 1.3333, "x": -5.19, "y": 0 }
				]
			}
		}
	},
	"Crouch Walk": {
		"slots": {
			"Foot2": {
				"attachment": [
					{ "time": 0, "name": "Survivor Sheet" }
				]
			}
		},
		"bones": {
			"Body": {
				"rotate": [
					{ "time": 0, "angle": 0 }
				],
				"translate": [
					{ "time": 0, "x": 0.26, "y": -9.14 },
					{ "time": 0.3333, "x": -0.82, "y": -7.81 },
					{ "time": 0.6667, "x": 0.26, "y": -9.14 },
					{ "time": 1, "x": -0.82, "y": -7.81 },
					{ "time": 1.3333, "x": 0.26, "y": -9.14 }
				]
			},
			"Right Leg Container": {
				"rotate": [
					{ "time": 0, "angle": -27.5 },
					{ "time": 0.3, "angle": 22.84 },
					{ "time": 0.3667, "angle": 1.4 },
					{ "time": 0.8667, "angle": -0.58 },
					{ "time": 1, "angle": -36.67 },
					{ "time": 1.3333, "angle": -27.5 }
				],
				"translate": [
					{ "time": 0, "x": 2.12, "y": 5.48 },
					{ "time": 0.3667, "x": 12.87, "y": 0.14 },
					{ "time": 0.8667, "x": -6.82, "y": 0.05 },
					{ "time": 1, "x": -13.38, "y": 3.41 },
					{ "time": 1.3333, "x": 2.12, "y": 5.48 }
				]
			},
			"Left Leg Container": {
				"rotate": [
					{ "time": 0, "angle": 0 },
					{ "time": 0.3667, "angle": -24.39 },
					{ "time": 0.4333, "angle": -48.75 },
					{ "time": 0.9333, "angle": 27.43 },
					{ "time": 1, "angle": 2.65 },
					{ "time": 1.3333, "angle": 0 }
				],
				"translate": [
					{ "time": 0, "x": 0.99, "y": 0 },
					{ "time": 0.3667, "x": -10.18, "y": 1.45 },
					{ "time": 0.4333, "x": -4.37, "y": 3.99 },
					{ "time": 0.9333, "x": 18.74, "y": 0.36 },
					{ "time": 1.3333, "x": 0.99, "y": 0 }
				]
			}
		}
	},
	"Crouch Walk Back": {
		"slots": {
			"Foot2": {
				"attachment": [
					{ "time": 0, "name": "Survivor Sheet" }
				]
			}
		},
		"bones": {
			"Body": {
				"rotate": [
					{ "time": 0, "angle": 0 }
				],
				"translate": [
					{ "time": 0, "x": 0.26, "y": -9.14 },
					{ "time": 0.3667, "x": -0.82, "y": -7.81 },
					{ "time": 0.7333, "x": 0.26, "y": -9.14 },
					{ "time": 1.1333, "x": -0.82, "y": -7.81 },
					{ "time": 1.5, "x": 0.26, "y": -9.14 }
				]
			},
			"Right Leg Container": {
				"rotate": [
					{ "time": 0, "angle": -27.5 },
					{ "time": 0.3667, "angle": -36.67 },
					{ "time": 0.5333, "angle": -0.58 },
					{ "time": 1.1, "angle": 1.4 },
					{ "time": 1.1667, "angle": 22.84 },
					{ "time": 1.5, "angle": -27.5 }
				],
				"translate": [
					{ "time": 0, "x": 2.12, "y": 5.48 },
					{ "time": 0.3667, "x": -13.38, "y": 3.41 },
					{ "time": 0.5333, "x": -6.82, "y": 0.05 },
					{ "time": 1.1, "x": 12.87, "y": 0.14 },
					{ "time": 1.5, "x": 2.12, "y": 5.48 }
				]
			},
			"Left Leg Container": {
				"rotate": [
					{ "time": 0, "angle": 0 },
					{ "time": 0.3667, "angle": 2.65 },
					{ "time": 0.4333, "angle": 27.43 },
					{ "time": 1, "angle": -48.75 },
					{ "time": 1.1, "angle": -24.39 },
					{ "time": 1.5, "angle": 0 }
				],
				"translate": [
					{ "time": 0, "x": 0.99, "y": 0 },
					{ "time": 0.4333, "x": 18.74, "y": 0.36 },
					{ "time": 1, "x": -4.37, "y": 3.99 },
					{ "time": 1.1, "x": -10.18, "y": 1.45 },
					{ "time": 1.5, "x": 0.99, "y": 0 }
				]
			}
		}
	},
	"Idle": {
		"slots": {
			"Foot2": {
				"attachment": [
					{ "time": 0, "name": "Survivor Sheet2" }
				]
			}
		},
		"bones": {
			"Body": {
				"translate": [
					{ "time": 0, "x": -1.43, "y": 0 },
					{ "time": 0.5, "x": 0, "y": 0.54 },
					{ "time": 1, "x": -1.43, "y": 0 }
				]
			},
			"Hands": {
				"rotate": [
					{ "time": 0, "angle": 0 }
				]
			}
		},
		"deform": {
			"default": {
				"Foot2": {
					"Survivor Sheet2": [
						{ "time": 0 }
					]
				}
			}
		}
	},
	"Run": {
		"slots": {
			"Foot2": {
				"attachment": [
					{ "time": 0, "name": "Survivor Sheet" }
				]
			}
		},
		"bones": {
			"Right Leg Container": {
				"rotate": [
					{ "time": 0, "angle": -68.23 },
					{ "time": 0.2667, "angle": 34.52 },
					{ "time": 0.3333, "angle": 2.54 },
					{ "time": 0.5, "angle": 0.57 },
					{ "time": 0.6667, "angle": -18.29 },
					{ "time": 0.7333, "angle": -78.07 },
					{ "time": 1, "angle": -68.23 }
				],
				"translate": [
					{ "time": 0, "x": -10.74, "y": 9.67 },
					{ "time": 0.2667, "x": 16.47, "y": 3.94 },
					{ "time": 0.3333, "x": 10.41, "y": 0.32 },
					{ "time": 0.5, "x": -4.74, "y": 0.11 },
					{ "time": 0.6667, "x": -16.99, "y": 2.49 },
					{ "time": 0.7333, "x": -21.3, "y": 10.2 },
					{ "time": 1, "x": -10.74, "y": 9.67 }
				]
			},
			"Left Leg Container": {
				"rotate": [
					{ "time": 0, "angle": 0 },
					{ "time": 0.2, "angle": -4.59 },
					{ "time": 0.2667, "angle": -59.6 },
					{ "time": 0.5, "angle": -64.44 },
					{ "time": 0.7333, "angle": 37.52 },
					{ "time": 0.8, "angle": 4.96 },
					{ "time": 1, "angle": 0 }
				],
				"translate": [
					{ "time": 0, "x": 4.48, "y": 0 },
					{ "time": 0.2, "x": -9.22, "y": 0.96 },
					{ "time": 0.2667, "x": -13.78, "y": 7.16 },
					{ "time": 0.5, "x": 0.54, "y": 7.43 },
					{ "time": 0.7333, "x": 20.58, "y": 4.12 },
					{ "time": 0.8, "x": 16.56, "y": -0.06 },
					{ "time": 1, "x": 4.48, "y": 0 }
				]
			},
			"Body": {
				"translate": [
					{
						"time": 0,
						"x": 0,
						"y": -2.52,
						"curve": [ 0.055, 0, 0.622, 1 ]
					},
					{ "time": 0.2667, "x": 0, "y": 0 },
					{
						"time": 0.5,
						"x": 0,
						"y": -2.52,
						"curve": [ 0.055, 0, 0.361, 1 ]
					},
					{ "time": 0.7333, "x": 0, "y": 0 },
					{ "time": 1, "x": 0, "y": -2.52 }
				]
			}
		}
	},
	"Walk": {
		"slots": {
			"Foot2": {
				"attachment": [
					{ "time": 0, "name": "Survivor Sheet" }
				]
			}
		},
		"bones": {
			"Left Leg Container": {
				"rotate": [
					{ "time": 0, "angle": 2.82 },
					{ "time": 0.2667, "angle": 4.52 },
					{ "time": 0.3333, "angle": -37.37 },
					{ "time": 0.5, "angle": -33.97 },
					{ "time": 0.7333, "angle": 17.92 },
					{ "time": 0.7667, "angle": 1.96 },
					{ "time": 1, "angle": 2.82 }
				],
				"translate": [
					{ "time": 0, "x": 5.08, "y": 0 },
					{ "time": 0.2667, "x": -8.88, "y": -0.25 },
					{ "time": 0.3333, "x": -13.88, "y": 4.85 },
					{
						"time": 0.5,
						"x": -2.5,
						"y": 6.31,
						"curve": [ 0.071, 0, 0.421, 1 ]
					},
					{ "time": 0.7667, "x": 13.14, "y": -0.09 },
					{ "time": 1, "x": 5.08, "y": 0 }
				]
			},
			"Right Leg Container": {
				"rotate": [
					{ "time": 0, "angle": -56.48 },
					{ "time": 0.2333, "angle": 19.59 },
					{ "time": 0.2667, "angle": 0.5 },
					{ "time": 0.5, "angle": 0.68 },
					{ "time": 0.7667, "angle": 0.59 },
					{ "time": 1, "angle": -56.48 }
				],
				"translate": [
					{
						"time": 0,
						"x": -13.45,
						"y": 7.71,
						"curve": [ 0.083, 0, 0.663, 1 ]
					},
					{ "time": 0.2667, "x": 7.56, "y": 0.29 },
					{ "time": 0.5, "x": -0.35, "y": 0.2 },
					{ "time": 0.7667, "x": -12.17, "y": 0.06 },
					{ "time": 1, "x": -13.45, "y": 7.71 }
				]
			},
			"Body": {
				"translate": [
					{ "time": 0, "x": -0.66, "y": 1.8 },
					{ "time": 0.2667, "x": -0.66, "y": -0.06 },
					{ "time": 0.5, "x": -0.66, "y": 1.8 },
					{ "time": 0.7667, "x": -0.66, "y": -0.06 },
					{ "time": 1, "x": -0.66, "y": 1.8 }
				]
			}
		}
	},
	"Walk Back": {
		"slots": {
			"Foot2": {
				"attachment": [
					{ "time": 0, "name": "Survivor Sheet" }
				]
			}
		},
		"bones": {
			"Left Leg Container": {
				"rotate": [
					{ "time": 0, "angle": 2.82 },
					{ "time": 0.2667, "angle": 1.96 },
					{ "time": 0.3, "angle": 17.92 },
					{ "time": 0.6, "angle": -33.97 },
					{ "time": 0.7667, "angle": -37.37 },
					{ "time": 0.8667, "angle": 4.52 },
					{ "time": 1.1667, "angle": 2.82 }
				],
				"translate": [
					{ "time": 0, "x": 5.08, "y": 0 },
					{ "time": 0.2667, "x": 13.14, "y": -0.09 },
					{
						"time": 0.6,
						"x": -2.5,
						"y": 6.31,
						"curve": [ 0.071, 0, 0.421, 1 ]
					},
					{ "time": 0.7667, "x": -13.88, "y": 4.85 },
					{ "time": 0.8667, "x": -8.88, "y": -0.25 },
					{ "time": 1.1667, "x": 5.08, "y": 0 }
				]
			},
			"Right Leg Container": {
				"rotate": [
					{ "time": 0, "angle": -56.48 },
					{ "time": 0.2667, "angle": 0.59 },
					{ "time": 0.5667, "angle": 0.68 },
					{ "time": 0.8667, "angle": 0.5 },
					{ "time": 0.9, "angle": 19.59 },
					{ "time": 1.1667, "angle": -56.48 }
				],
				"translate": [
					{ "time": 0, "x": -13.45, "y": 7.71 },
					{ "time": 0.2667, "x": -12.17, "y": 0.06 },
					{ "time": 0.5667, "x": -0.35, "y": 0.2 },
					{ "time": 0.8667, "x": 7.56, "y": 0.29 },
					{ "time": 1.1667, "x": -13.45, "y": 7.71 }
				]
			},
			"Body": {
				"translate": [
					{ "time": 0, "x": -0.66, "y": 1.8 },
					{ "time": 0.3, "x": -0.66, "y": -0.06 },
					{ "time": 0.5667, "x": -0.66, "y": 1.8 },
					{ "time": 0.9, "x": -0.66, "y": -0.06 },
					{ "time": 1.1667, "x": -0.66, "y": 1.8 }
				]
			}
		}
	}
}
}